nwce/__init__.py
nwce/nxos.re.txt
nwce-0.2.0.dist-info/LICENSE.md
nwce-0.2.0.dist-info/WHEEL
nwce-0.2.0.dist-info/METADATA
nwce-0.2.0.dist-info/RECORD
