Metadata-Version: 2.1
Name: nwce
Version: 0.2.0
Summary: NWCE stands for NetWork Configuration Editor and helps you parsing Cisco configurations
Home-page: https://github.com/desnoe/nwce
License: MIT
Keywords: cisco,parser
Author: DESNOË Olivier (Canal Plus)
Author-email: olivier.desnoe@canal-plus.com
Requires-Python: >=3.7,<4.0
Classifier: License :: OSI Approved :: MIT License
Classifier: Programming Language :: Python :: 3
Classifier: Programming Language :: Python :: 3.10
Classifier: Programming Language :: Python :: 3.7
Classifier: Programming Language :: Python :: 3.8
Classifier: Programming Language :: Python :: 3.9
